flumes/__init__.py
flumes/alembic/README
flumes/alembic/env.py
flumes/alembic/script.py.mako
flumes/alembic/versions/242be726f817_.py
flumes/alembic/versions/30374e2904cd_.py
flumes/alembic/versions/a0b003abaac8_.py
flumes/alembic/versions/ad35ceceeb92_.py
flumes/alembic/versions/e827c1336bb4_first_commit.py
flumes/config.py
flumes/discoverer.py
flumes/options.py
flumes/schema.py
flumes-0.1.23.dist-info/entry_points.txt
flumes-0.1.23.dist-info/LICENSE.LGPL
flumes-0.1.23.dist-info/WHEEL
flumes-0.1.23.dist-info/METADATA
flumes-0.1.23.dist-info/RECORD
