Metadata-Version: 2.1
Name: flumes
Version: 0.1.23
Summary: Scan and index your media files
Home-page: https://fluendo.com
License: LGPL-2.1-only
Author: Jorge Zapata
Author-email: jorgeluis.zapata@gmail.com
Requires-Python: >=3.9,<4.0
Classifier: License :: OSI Approved
Classifier: Programming Language :: Python :: 3
Classifier: Programming Language :: Python :: 3.9
Classifier: Programming Language :: Python :: 3.10
Classifier: Programming Language :: Python :: 3.11
Requires-Dist: PyGObject (>=3.42.0,<4.0.0)
Requires-Dist: SQLAlchemy (>=1.4.26,<2.0.0)
Requires-Dist: alembic (>=1.7.5,<2.0.0)
Requires-Dist: packaging (>=21.3,<22.0)
Requires-Dist: python-dateutil (>=2.8.2,<3.0.0)
Project-URL: Repository, https://github.com/fluendo/flumes
